{
  "match_id": "296afb1a",
  "timestamp": "2026-03-12T18:27:40.048220+00:00",
  "duration_turns": 31,
  "map_id": "open_arena_large",
  "match_type": "pvp",
  "winner": "team_a",
  "config": {
    "max_players": 11,
    "tick_rate": 1.0,
    "ai_opponents": 5,
    "ai_allies": 5,
    "ai_opponent_classes": [
      "confessor",
      "crusader",
      "hexblade",
      "inquisitor",
      "revenant"
    ],
    "ai_ally_classes": [
      "crusader",
      "hexblade",
      "inquisitor",
      "ranger",
      "shaman"
    ]
  },
  "teams": {
    "team_a": [
      {
        "unit_id": "ai-2e99d1",
        "username": "Crusader",
        "class_id": "crusader",
        "team": "a",
        "is_ai": true,
        "base_hp": 135,
        "base_melee_damage": 0,
        "base_armor": 6
      },
      {
        "unit_id": "ai-289784",
        "username": "Hexblade",
        "class_id": "hexblade",
        "team": "a",
        "is_ai": true,
        "base_hp": 110,
        "base_melee_damage": 0,
        "base_armor": 5
      },
      {
        "unit_id": "ai-53fbfb",
        "username": "Inquisitor",
        "class_id": "inquisitor",
        "team": "a",
        "is_ai": true,
        "base_hp": 90,
        "base_melee_damage": 0,
        "base_armor": 4
      },
      {
        "unit_id": "ai-e82373",
        "username": "Ranger",
        "class_id": "ranger",
        "team": "a",
        "is_ai": true,
        "base_hp": 80,
        "base_melee_damage": 0,
        "base_armor": 2
      },
      {
        "unit_id": "ai-ef2b85",
        "username": "Shaman",
        "class_id": "shaman",
        "team": "a",
        "is_ai": true,
        "base_hp": 95,
        "base_melee_damage": 0,
        "base_armor": 3
      }
    ],
    "team_b": [
      {
        "unit_id": "ai-1b84e7",
        "username": "Confessor",
        "class_id": "confessor",
        "team": "b",
        "is_ai": true,
        "base_hp": 100,
        "base_melee_damage": 0,
        "base_armor": 3
      },
      {
        "unit_id": "ai-7a35f7",
        "username": "Crusader 2",
        "class_id": "crusader",
        "team": "b",
        "is_ai": true,
        "base_hp": 135,
        "base_melee_damage": 0,
        "base_armor": 6
      },
      {
        "unit_id": "ai-7fe566",
        "username": "Hexblade 2",
        "class_id": "hexblade",
        "team": "b",
        "is_ai": true,
        "base_hp": 110,
        "base_melee_damage": 0,
        "base_armor": 5
      },
      {
        "unit_id": "ai-cb0908",
        "username": "Inquisitor 2",
        "class_id": "inquisitor",
        "team": "b",
        "is_ai": true,
        "base_hp": 90,
        "base_melee_damage": 0,
        "base_armor": 4
      },
      {
        "unit_id": "ai-9e6803",
        "username": "Revenant",
        "class_id": "revenant",
        "team": "b",
        "is_ai": true,
        "base_hp": 130,
        "base_melee_damage": 0,
        "base_armor": 6
      }
    ]
  },
  "unit_stats": {
    "ai-2e99d1": {
      "unit_id": "ai-2e99d1",
      "username": "Crusader",
      "class_id": "crusader",
      "team": "a",
      "is_ai": true,
      "status": "survived",
      "damage_dealt": 117,
      "damage_taken": 166,
      "healing_done": 60,
      "kills": 1,
      "boss_kills": 0,
      "deaths": 0,
      "turns_survived": 31,
      "items_looted": 0,
      "highest_hit": 11,
      "overkill_damage": 0
    },
    "ai-289784": {
      "unit_id": "ai-289784",
      "username": "Hexblade",
      "class_id": "hexblade",
      "team": "a",
      "is_ai": true,
      "status": "survived",
      "damage_dealt": 101,
      "damage_taken": 135,
      "healing_done": 0,
      "kills": 1,
      "boss_kills": 0,
      "deaths": 0,
      "turns_survived": 31,
      "items_looted": 0,
      "highest_hit": 14,
      "overkill_damage": 0
    },
    "ai-53fbfb": {
      "unit_id": "ai-53fbfb",
      "username": "Inquisitor",
      "class_id": "inquisitor",
      "team": "a",
      "is_ai": true,
      "status": "survived",
      "damage_dealt": 179,
      "damage_taken": 16,
      "healing_done": 0,
      "kills": 0,
      "boss_kills": 0,
      "deaths": 0,
      "turns_survived": 31,
      "items_looted": 0,
      "highest_hit": 30,
      "overkill_damage": 0
    },
    "ai-e82373": {
      "unit_id": "ai-e82373",
      "username": "Ranger",
      "class_id": "ranger",
      "team": "a",
      "is_ai": true,
      "status": "survived",
      "damage_dealt": 188,
      "damage_taken": 0,
      "healing_done": 0,
      "kills": 3,
      "boss_kills": 0,
      "deaths": 0,
      "turns_survived": 31,
      "items_looted": 0,
      "highest_hit": 35,
      "overkill_damage": 0
    },
    "ai-ef2b85": {
      "unit_id": "ai-ef2b85",
      "username": "Shaman",
      "class_id": "shaman",
      "team": "a",
      "is_ai": true,
      "status": "survived",
      "damage_dealt": 47,
      "damage_taken": 30,
      "healing_done": 238,
      "kills": 0,
      "boss_kills": 0,
      "deaths": 0,
      "turns_survived": 31,
      "items_looted": 0,
      "highest_hit": 8,
      "overkill_damage": 0
    },
    "ai-1b84e7": {
      "unit_id": "ai-1b84e7",
      "username": "Confessor",
      "class_id": "confessor",
      "team": "b",
      "is_ai": true,
      "status": "died",
      "damage_dealt": 6,
      "damage_taken": 103,
      "healing_done": 38,
      "kills": 0,
      "boss_kills": 0,
      "deaths": 1,
      "turns_survived": 16,
      "items_looted": 0,
      "highest_hit": 6,
      "overkill_damage": 0
    },
    "ai-7a35f7": {
      "unit_id": "ai-7a35f7",
      "username": "Crusader 2",
      "class_id": "crusader",
      "team": "b",
      "is_ai": true,
      "status": "died",
      "damage_dealt": 85,
      "damage_taken": 141,
      "healing_done": 30,
      "kills": 1,
      "boss_kills": 0,
      "deaths": 1,
      "turns_survived": 28,
      "items_looted": 0,
      "highest_hit": 13,
      "overkill_damage": 0
    },
    "ai-7fe566": {
      "unit_id": "ai-7fe566",
      "username": "Hexblade 2",
      "class_id": "hexblade",
      "team": "b",
      "is_ai": true,
      "status": "died",
      "damage_dealt": 98,
      "damage_taken": 88,
      "healing_done": 0,
      "kills": 0,
      "boss_kills": 0,
      "deaths": 1,
      "turns_survived": 30,
      "items_looted": 0,
      "highest_hit": 13,
      "overkill_damage": 0
    },
    "ai-cb0908": {
      "unit_id": "ai-cb0908",
      "username": "Inquisitor 2",
      "class_id": "inquisitor",
      "team": "b",
      "is_ai": true,
      "status": "died",
      "damage_dealt": 17,
      "damage_taken": 100,
      "healing_done": 0,
      "kills": 0,
      "boss_kills": 0,
      "deaths": 1,
      "turns_survived": 8,
      "items_looted": 0,
      "highest_hit": 17,
      "overkill_damage": 0
    },
    "ai-9e6803": {
      "unit_id": "ai-9e6803",
      "username": "Revenant",
      "class_id": "revenant",
      "team": "b",
      "is_ai": true,
      "status": "died",
      "damage_dealt": 141,
      "damage_taken": 169,
      "healing_done": 39,
      "kills": 0,
      "boss_kills": 0,
      "deaths": 1,
      "turns_survived": 29,
      "items_looted": 0,
      "highest_hit": 19,
      "overkill_damage": 0
    }
  },
  "timeline": [
    {
      "turn": 1,
      "events": [
        {
          "type": "move",
          "unit": "ai-2e99d1",
          "to": [
            2,
            1
          ]
        },
        {
          "type": "move",
          "unit": "ai-289784",
          "to": [
            1,
            2
          ]
        },
        {
          "type": "move",
          "unit": "ai-53fbfb",
          "to": [
            3,
            2
          ]
        },
        {
          "type": "move",
          "unit": "ai-ef2b85",
          "to": [
            4,
            1
          ]
        },
        {
          "type": "move",
          "unit": "ai-1b84e7",
          "to": [
            15,
            18
          ]
        },
        {
          "type": "move",
          "unit": "ai-7a35f7",
          "to": [
            16,
            15
          ]
        },
        {
          "type": "move",
          "unit": "ai-cb0908",
          "to": [
            14,
            16
          ]
        },
        {
          "type": "move",
          "unit": "ai-9e6803",
          "to": [
            14,
            15
          ]
        }
      ]
    },
    {
      "turn": 2,
      "events": [
        {
          "type": "move",
          "unit": "ai-2e99d1",
          "to": [
            3,
            1
          ]
        },
        {
          "type": "move",
          "unit": "ai-289784",
          "to": [
            2,
            3
          ]
        },
        {
          "type": "move",
          "unit": "ai-53fbfb",
          "to": [
            4,
            3
          ]
        },
        {
          "type": "move",
          "unit": "ai-e82373",
          "to": [
            2,
            1
          ]
        },
        {
          "type": "move",
          "unit": "ai-ef2b85",
          "to": [
            5,
            2
          ]
        },
        {
          "type": "move",
          "unit": "ai-1b84e7",
          "to": [
            14,
            17
          ]
        },
        {
          "type": "move",
          "unit": "ai-7a35f7",
          "to": [
            15,
            14
          ]
        },
        {
          "type": "move",
          "unit": "ai-7fe566",
          "to": [
            15,
            17
          ]
        },
        {
          "type": "move",
          "unit": "ai-cb0908",
          "to": [
            13,
            15
          ]
        },
        {
          "type": "move",
          "unit": "ai-9e6803",
          "to": [
            13,
            14
          ]
        }
      ]
    },
    {
      "turn": 3,
      "events": [
        {
          "type": "move",
          "unit": "ai-2e99d1",
          "to": [
            4,
            2
          ]
        },
        {
          "type": "move",
          "unit": "ai-289784",
          "to": [
            3,
            4
          ]
        },
        {
          "type": "move",
          "unit": "ai-53fbfb",
          "to": [
            5,
            4
          ]
        },
        {
          "type": "move",
          "unit": "ai-e82373",
          "to": [
            3,
            2
          ]
        },
        {
          "type": "move",
          "unit": "ai-ef2b85",
          "to": [
            6,
            3
          ]
        },
        {
          "type": "move",
          "unit": "ai-1b84e7",
          "to": [
            13,
            16
          ]
        },
        {
          "type": "move",
          "unit": "ai-7a35f7",
          "to": [
            14,
            13
          ]
        },
        {
          "type": "move",
          "unit": "ai-7fe566",
          "to": [
            14,
            16
          ]
        },
        {
          "type": "move",
          "unit": "ai-cb0908",
          "to": [
            12,
            14
          ]
        },
        {
          "type": "move",
          "unit": "ai-9e6803",
          "to": [
            12,
            13
          ]
        }
      ]
    },
    {
      "turn": 4,
      "events": [
        {
          "type": "move",
          "unit": "ai-2e99d1",
          "to": [
            5,
            3
          ]
        },
        {
          "type": "move",
          "unit": "ai-289784",
          "to": [
            4,
            5
          ]
        },
        {
          "type": "move",
          "unit": "ai-53fbfb",
          "to": [
            6,
            5
          ]
        },
        {
          "type": "move",
          "unit": "ai-e82373",
          "to": [
            4,
            3
          ]
        },
        {
          "type": "move",
          "unit": "ai-ef2b85",
          "to": [
            7,
            4
          ]
        },
        {
          "type": "move",
          "unit": "ai-1b84e7",
          "to": [
            12,
            15
          ]
        },
        {
          "type": "move",
          "unit": "ai-7a35f7",
          "to": [
            13,
            12
          ]
        },
        {
          "type": "move",
          "unit": "ai-7fe566",
          "to": [
            13,
            15
          ]
        },
        {
          "type": "move",
          "unit": "ai-cb0908",
          "to": [
            11,
            13
          ]
        },
        {
          "type": "move",
          "unit": "ai-9e6803",
          "to": [
            11,
            12
          ]
        }
      ]
    },
    {
      "turn": 5,
      "events": [
        {
          "type": "move",
          "unit": "ai-2e99d1",
          "to": [
            6,
            4
          ]
        },
        {
          "type": "move",
          "unit": "ai-289784",
          "to": [
            5,
            6
          ]
        },
        {
          "type": "move",
          "unit": "ai-53fbfb",
          "to": [
            7,
            6
          ]
        },
        {
          "type": "move",
          "unit": "ai-e82373",
          "to": [
            5,
            4
          ]
        },
        {
          "type": "move",
          "unit": "ai-ef2b85",
          "to": [
            8,
            5
          ]
        },
        {
          "type": "move",
          "unit": "ai-1b84e7",
          "to": [
            11,
            14
          ]
        },
        {
          "type": "move",
          "unit": "ai-7a35f7",
          "to": [
            12,
            11
          ]
        },
        {
          "type": "move",
          "unit": "ai-7fe566",
          "to": [
            12,
            14
          ]
        },
        {
          "type": "move",
          "unit": "ai-cb0908",
          "to": [
            10,
            12
          ]
        },
        {
          "type": "move",
          "unit": "ai-9e6803",
          "to": [
            10,
            11
          ]
        }
      ]
    },
    {
      "turn": 6,
      "events": [
        {
          "type": "move",
          "unit": "ai-2e99d1",
          "to": [
            5,
            5
          ]
        },
        {
          "type": "move",
          "unit": "ai-289784",
          "to": [
            6,
            7
          ]
        },
        {
          "type": "move",
          "unit": "ai-53fbfb",
          "to": [
            8,
            7
          ]
        },
        {
          "type": "move",
          "unit": "ai-e82373",
          "to": [
            6,
            5
          ]
        },
        {
          "type": "move",
          "unit": "ai-ef2b85",
          "to": [
            9,
            6
          ]
        },
        {
          "type": "move",
          "unit": "ai-9e6803",
          "to": [
            9,
            11
          ]
        },
        {
          "type": "buff",
          "src": "ai-1b84e7",
          "tgt": "ai-1b84e7",
          "buff": "shield_of_faith"
        },
        {
          "type": "buff",
          "src": "ai-7a35f7",
          "tgt": "ai-7a35f7",
          "buff": "bulwark"
        },
        {
          "type": "buff",
          "src": "ai-7fe566",
          "tgt": "ai-7fe566",
          "buff": "ward"
        }
      ]
    },
    {
      "turn": 7,
      "events": [
        {
          "type": "move",
          "unit": "ai-1b84e7",
          "to": [
            10,
            13
          ]
        },
        {
          "type": "move",
          "unit": "ai-7a35f7",
          "to": [
            11,
            10
          ]
        },
        {
          "type": "buff",
          "src": "ai-2e99d1",
          "tgt": "ai-2e99d1",
          "buff": "bulwark"
        },
        {
          "type": "buff",
          "src": "ai-289784",
          "tgt": "ai-9e6803",
          "buff": "wither"
        },
        {
          "type": "buff",
          "src": "ai-53fbfb",
          "tgt": "ai-cb0908",
          "buff": "seal_of_judgment"
        },
        {
          "type": "damage",
          "src": "ai-e82373",
          "tgt": null,
          "dmg": 9,
          "skill": "volley",
          "crit": false
        },
        {
          "type": "buff",
          "src": "ai-e82373",
          "tgt": "ai-e82373",
          "buff": "volley"
        },
        {
          "type": "buff",
          "src": "ai-ef2b85",
          "tgt": "ai-ef2b85",
          "buff": "searing_totem"
        },
        {
          "type": "buff",
          "src": "ai-cb0908",
          "tgt": "ai-2e99d1",
          "buff": "seal_of_judgment"
        },
        {
          "type": "buff",
          "src": "ai-9e6803",
          "tgt": "ai-289784",
          "buff": "grave_chains"
        }
      ]
    },
    {
      "turn": 8,
      "events": [
        {
          "type": "damage",
          "src": "ai-9e6803",
          "tgt": "ai-9e6803",
          "dmg": 8,
          "skill": "wither",
          "crit": false
        },
        {
          "type": "damage",
          "src": "ai-ef2b85",
          "tgt": "ai-7fe566",
          "dmg": 1,
          "skill": "searing_totem",
          "crit": false
        },
        {
          "type": "damage",
          "src": "ai-ef2b85",
          "tgt": "ai-cb0908",
          "dmg": 1,
          "skill": "searing_totem",
          "crit": false
        },
        {
          "type": "damage",
          "src": "ai-ef2b85",
          "tgt": "ai-9e6803",
          "dmg": 1,
          "skill": "searing_totem",
          "crit": false
        },
        {
          "type": "move",
          "unit": "ai-2e99d1",
          "to": [
            4,
            6
          ]
        },
        {
          "type": "move",
          "unit": "ai-1b84e7",
          "to": [
            9,
            12
          ]
        },
        {
          "type": "move",
          "unit": "ai-7a35f7",
          "to": [
            11,
            9
          ]
        },
        {
          "type": "move",
          "unit": "ai-9e6803",
          "to": [
            8,
            10
          ]
        },
        {
          "type": "buff",
          "src": "ai-289784",
          "tgt": "ai-289784",
          "buff": "ward"
        },
        {
          "type": "damage",
          "src": "ai-53fbfb",
          "tgt": "ai-cb0908",
          "dmg": 30,
          "skill": "rebuke",
          "crit": false
        },
        {
          "type": "damage",
          "src": "ai-e82373",
          "tgt": "ai-cb0908",
          "dmg": 12,
          "skill": "crippling_shot",
          "crit": false
        },
        {
          "type": "buff",
          "src": "ai-e82373",
          "tgt": "ai-cb0908",
          "buff": "crippling_shot"
        },
        {
          "type": "buff",
          "src": "ai-ef2b85",
          "tgt": "ai-ef2b85",
          "buff": "earthgrasp"
        },
        {
          "type": "damage",
          "src": "ai-cb0908",
          "tgt": "ai-2e99d1",
          "dmg": 17,
          "skill": "rebuke",
          "crit": false
        }
      ]
    },
    {
      "turn": 9,
      "events": [
        {
          "type": "damage",
          "src": "ai-9e6803",
          "tgt": "ai-9e6803",
          "dmg": 8,
          "skill": "wither",
          "crit": false
        },
        {
          "type": "damage",
          "src": "ai-ef2b85",
          "tgt": "ai-7fe566",
          "dmg": 1,
          "skill": "searing_totem",
          "crit": false
        },
        {
          "type": "damage",
          "src": "ai-ef2b85",
          "tgt": "ai-cb0908",
          "dmg": 1,
          "skill": "searing_totem",
          "crit": false
        },
        {
          "type": "damage",
          "src": "ai-ef2b85",
          "tgt": "ai-9e6803",
          "dmg": 1,
          "skill": "searing_totem",
          "crit": false
        },
        {
          "type": "move",
          "unit": "ai-2e99d1",
          "to": [
            5,
            7
          ]
        },
        {
          "type": "move",
          "unit": "ai-289784",
          "to": [
            7,
            8
          ]
        },
        {
          "type": "move",
          "unit": "ai-7a35f7",
          "to": [
            10,
            8
          ]
        },
        {
          "type": "move",
          "unit": "ai-7fe566",
          "to": [
            9,
            11
          ]
        },
        {
          "type": "damage",
          "src": "ai-53fbfb",
          "tgt": "ai-cb0908",
          "dmg": 21,
          "skill": "power_shot",
          "crit": false
        },
        {
          "type": "damage",
          "src": "ai-e82373",
          "tgt": "ai-cb0908",
          "dmg": 35,
          "skill": "power_shot",
          "crit": false
        },
        {
          "type": "death",
          "unit": "ai-cb0908",
          "killer": "ai-e82373"
        }
      ]
    },
    {
      "turn": 10,
      "events": [
        {
          "type": "damage",
          "src": "ai-9e6803",
          "tgt": "ai-9e6803",
          "dmg": 8,
          "skill": "wither",
          "crit": false
        },
        {
          "type": "damage",
          "src": "ai-ef2b85",
          "tgt": "ai-7a35f7",
          "dmg": 1,
          "skill": "searing_totem",
          "crit": false
        },
        {
          "type": "damage",
          "src": "ai-ef2b85",
          "tgt": "ai-7fe566",
          "dmg": 1,
          "skill": "searing_totem",
          "crit": false
        },
        {
          "type": "damage",
          "src": "ai-ef2b85",
          "tgt": "ai-9e6803",
          "dmg": 1,
          "skill": "searing_totem",
          "crit": false
        },
        {
          "type": "move",
          "unit": "ai-2e99d1",
          "to": [
            6,
            8
          ]
        },
        {
          "type": "move",
          "unit": "ai-289784",
          "to": [
            7,
            9
          ]
        },
        {
          "type": "move",
          "unit": "ai-53fbfb",
          "to": [
            7,
            6
          ]
        },
        {
          "type": "move",
          "unit": "ai-ef2b85",
          "to": [
            9,
            7
          ]
        },
        {
          "type": "damage",
          "src": "ai-1b84e7",
          "tgt": "ai-2e99d1",
          "dmg": 6,
          "skill": "exorcism",
          "crit": false
        },
        {
          "type": "buff",
          "src": "ai-7a35f7",
          "tgt": "ai-7a35f7",
          "buff": "taunt"
        },
        {
          "type": "buff",
          "src": "ai-7fe566",
          "tgt": "ai-2e99d1",
          "buff": "wither"
        },
        {
          "type": "buff",
          "src": "ai-9e6803",
          "tgt": "ai-9e6803",
          "buff": "grave_thorns"
        }
      ]
    },
    {
      "turn": 11,
      "events": [
        {
          "type": "damage",
          "src": "ai-2e99d1",
          "tgt": "ai-2e99d1",
          "dmg": 8,
          "skill": "wither",
          "crit": false
        },
        {
          "type": "damage",
          "src": "ai-ef2b85",
          "tgt": "ai-7a35f7",
          "dmg": 1,
          "skill": "searing_totem",
          "crit": false
        },
        {
          "type": "damage",
          "src": "ai-ef2b85",
          "tgt": "ai-7fe566",
          "dmg": 1,
          "skill": "searing_totem",
          "crit": false
        },
        {
          "type": "damage",
          "src": "ai-ef2b85",
          "tgt": "ai-9e6803",
          "dmg": 1,
          "skill": "searing_totem",
          "crit": false
        },
        {
          "type": "move",
          "unit": "ai-e82373",
          "to": [
            7,
            5
          ]
        },
        {
          "type": "move",
          "unit": "ai-ef2b85",
          "to": [
            8,
            7
          ]
        },
        {
          "type": "move",
          "unit": "ai-1b84e7",
          "to": [
            8,
            11
          ]
        },
        {
          "type": "buff",
          "src": "ai-2e99d1",
          "tgt": "ai-2e99d1",
          "buff": "taunt"
        },
        {
          "type": "damage",
          "src": "ai-289784",
          "tgt": "ai-9e6803",
          "dmg": 8,
          "skill": "double_strike",
          "crit": false
        },
        {
          "type": "damage",
          "src": "ai-9e6803",
          "tgt": "ai-289784",
          "dmg": 19,
          "skill": "soul_rend",
          "crit": false
        },
        {
          "type": "buff",
          "src": "ai-9e6803",
          "tgt": "ai-289784",
          "buff": "soul_rend"
        },
        {
          "type": "damage",
          "src": "ai-53fbfb",
          "tgt": "ai-7a35f7",
          "dmg": 6,
          "skill": "ranged_attack",
          "crit": false
        }
      ]
    },
    {
      "turn": 12,
      "events": [
        {
          "type": "damage",
          "src": "ai-2e99d1",
          "tgt": "ai-2e99d1",
          "dmg": 8,
          "skill": "wither",
          "crit": false
        },
        {
          "type": "move",
          "unit": "ai-2e99d1",
          "to": [
            6,
            9
          ]
        },
        {
          "type": "move",
          "unit": "ai-e82373",
          "to": [
            6,
            6
          ]
        },
        {
          "type": "move",
          "unit": "ai-ef2b85",
          "to": [
            9,
            7
          ]
        },
        {
          "type": "move",
          "unit": "ai-7fe566",
          "to": [
            8,
            12
          ]
        },
        {
          "type": "move",
          "unit": "ai-9e6803",
          "to": [
            7,
            10
          ]
        },
        {
          "type": "buff",
          "src": "ai-53fbfb",
          "tgt": "ai-7a35f7",
          "buff": "seal_of_judgment"
        },
        {
          "type": "buff",
          "src": "ai-1b84e7",
          "tgt": "ai-9e6803",
          "buff": "shield_of_faith"
        },
        {
          "type": "buff",
          "src": "ai-7a35f7",
          "tgt": "ai-7a35f7",
          "buff": "bulwark"
        },
        {
          "type": "damage",
          "src": "ai-289784",
          "tgt": "ai-9e6803",
          "dmg": 4,
          "skill": "attack",
          "crit": false
        },
        {
          "type": "damage",
          "src": "ai-9e6803",
          "tgt": "ai-289784",
          "dmg": 12,
          "skill": "attack",
          "crit": false
        }
      ]
    },
    {
      "turn": 13,
      "events": [
        {
          "type": "damage",
          "src": "ai-2e99d1",
          "tgt": "ai-2e99d1",
          "dmg": 8,
          "skill": "wither",
          "crit": false
        },
        {
          "type": "move",
          "unit": "ai-53fbfb",
          "to": [
            8,
            7
          ]
        },
        {
          "type": "move",
          "unit": "ai-1b84e7",
          "to": [
            7,
            11
          ]
        },
        {
          "type": "damage",
          "src": "ai-2e99d1",
          "tgt": "ai-9e6803",
          "dmg": 1,
          "skill": "shield_bash",
          "crit": false
        },
        {
          "type": "buff",
          "src": "ai-2e99d1",
          "tgt": "ai-9e6803",
          "buff": "shield_bash"
        },
        {
          "type": "buff",
          "src": "ai-289784",
          "tgt": "ai-7a35f7",
          "buff": "wither"
        },
        {
          "type": "buff",
          "src": "ai-ef2b85",
          "tgt": "ai-ef2b85",
          "buff": "healing_totem"
        },
        {
          "type": "damage",
          "src": "ai-7a35f7",
          "tgt": "ai-ef2b85",
          "dmg": 6,
          "skill": "shield_bash",
          "crit": false
        },
        {
          "type": "buff",
          "src": "ai-7a35f7",
          "tgt": "ai-ef2b85",
          "buff": "shield_bash"
        },
        {
          "type": "buff",
          "src": "ai-7fe566",
          "tgt": "ai-7fe566",
          "buff": "ward"
        },
        {
          "type": "damage",
          "src": "ai-e82373",
          "tgt": "ai-7a35f7",
          "dmg": 5,
          "skill": "ranged_attack",
          "crit": false
        }
      ]
    },
    {
      "turn": 14,
      "events": [
        {
          "type": "damage",
          "src": "ai-7a35f7",
          "tgt": "ai-7a35f7",
          "dmg": 8,
          "skill": "wither",
          "crit": false
        },
        {
          "type": "heal",
          "src": "ai-ef2b85",
          "tgt": "ai-2e99d1",
          "amt": 8,
          "skill": "healing_totem"
        },
        {
          "type": "heal",
          "src": "ai-ef2b85",
          "tgt": "ai-289784",
          "amt": 8,
          "skill": "healing_totem"
        },
        {
          "type": "heal",
          "src": "ai-ef2b85",
          "tgt": "ai-ef2b85",
          "amt": 6,
          "skill": "healing_totem"
        },
        {
          "type": "move",
          "unit": "ai-1b84e7",
          "to": [
            6,
            10
          ]
        },
        {
          "type": "move",
          "unit": "ai-7a35f7",
          "to": [
            9,
            8
          ]
        },
        {
          "type": "buff",
          "src": "ai-2e99d1",
          "tgt": "ai-2e99d1",
          "buff": "bulwark"
        },
        {
          "type": "damage",
          "src": "ai-53fbfb",
          "tgt": "ai-1b84e7",
          "dmg": 25,
          "skill": "rebuke",
          "crit": false
        },
        {
          "type": "damage",
          "src": "ai-e82373",
          "tgt": "ai-1b84e7",
          "dmg": 11,
          "skill": "crippling_shot",
          "crit": false
        },
        {
          "type": "buff",
          "src": "ai-e82373",
          "tgt": "ai-1b84e7",
          "buff": "crippling_shot"
        },
        {
          "type": "damage",
          "src": "ai-289784",
          "tgt": "ai-9e6803",
          "dmg": 4,
          "skill": "attack",
          "crit": false
        }
      ]
    },
    {
      "turn": 15,
      "events": [
        {
          "type": "damage",
          "src": "ai-7a35f7",
          "tgt": "ai-7a35f7",
          "dmg": 8,
          "skill": "wither",
          "crit": false
        },
        {
          "type": "heal",
          "src": "ai-ef2b85",
          "tgt": "ai-2e99d1",
          "amt": 8,
          "skill": "healing_totem"
        },
        {
          "type": "heal",
          "src": "ai-ef2b85",
          "tgt": "ai-289784",
          "amt": 8,
          "skill": "healing_totem"
        },
        {
          "type": "move",
          "unit": "ai-53fbfb",
          "to": [
            7,
            6
          ]
        },
        {
          "type": "move",
          "unit": "ai-7a35f7",
          "to": [
            8,
            8
          ]
        },
        {
          "type": "buff",
          "src": "ai-289784",
          "tgt": "ai-289784",
          "buff": "ward"
        },
        {
          "type": "damage",
          "src": "ai-e82373",
          "tgt": null,
          "dmg": 14,
          "skill": "volley",
          "crit": false
        },
        {
          "type": "buff",
          "src": "ai-e82373",
          "tgt": "ai-e82373",
          "buff": "volley"
        },
        {
          "type": "buff",
          "src": "ai-ef2b85",
          "tgt": "ai-ef2b85",
          "buff": "searing_totem"
        },
        {
          "type": "heal",
          "src": "ai-1b84e7",
          "tgt": "ai-9e6803",
          "amt": 30,
          "skill": "heal"
        },
        {
          "type": "buff",
          "src": "ai-9e6803",
          "tgt": "ai-e82373",
          "buff": "grave_chains"
        },
        {
          "type": "damage",
          "src": "ai-2e99d1",
          "tgt": "ai-1b84e7",
          "dmg": 11,
          "skill": "attack",
          "crit": false
        }
      ]
    },
    {
      "turn": 16,
      "events": [
        {
          "type": "damage",
          "src": "ai-7a35f7",
          "tgt": "ai-7a35f7",
          "dmg": 8,
          "skill": "wither",
          "crit": false
        },
        {
          "type": "heal",
          "src": "ai-ef2b85",
          "tgt": "ai-2e99d1",
          "amt": 8,
          "skill": "healing_totem"
        },
        {
          "type": "heal",
          "src": "ai-ef2b85",
          "tgt": "ai-289784",
          "amt": 8,
          "skill": "healing_totem"
        },
        {
          "type": "damage",
          "src": "ai-ef2b85",
          "tgt": "ai-1b84e7",
          "dmg": 1,
          "skill": "searing_totem",
          "crit": false
        },
        {
          "type": "damage",
          "src": "ai-ef2b85",
          "tgt": "ai-7a35f7",
          "dmg": 1,
          "skill": "searing_totem",
          "crit": false
        },
        {
          "type": "damage",
          "src": "ai-ef2b85",
          "tgt": "ai-9e6803",
          "dmg": 1,
          "skill": "searing_totem",
          "crit": false
        },
        {
          "type": "move",
          "unit": "ai-53fbfb",
          "to": [
            6,
            5
          ]
        },
        {
          "type": "move",
          "unit": "ai-e82373",
          "to": [
            6,
            7
          ]
        },
        {
          "type": "damage",
          "src": "ai-289784",
          "tgt": "ai-1b84e7",
          "dmg": 14,
          "skill": "double_strike",
          "crit": false
        },
        {
          "type": "buff",
          "src": "ai-1b84e7",
          "tgt": "ai-1b84e7",
          "buff": "prayer"
        },
        {
          "type": "buff",
          "src": "ai-7a35f7",
          "tgt": "ai-7a35f7",
          "buff": "taunt"
        },
        {
          "type": "buff",
          "src": "ai-7fe566",
          "tgt": "ai-289784",
          "buff": "wither"
        },
        {
          "type": "damage",
          "src": "ai-9e6803",
          "tgt": "ai-2e99d1",
          "dmg": 10,
          "skill": "soul_rend",
          "crit": false
        },
        {
          "type": "buff",
          "src": "ai-9e6803",
          "tgt": "ai-2e99d1",
          "buff": "soul_rend"
        },
        {
          "type": "damage",
          "src": "ai-2e99d1",
          "tgt": "ai-1b84e7",
          "dmg": 11,
          "skill": "attack",
          "crit": false
        }
      ]
    },
    {
      "turn": 17,
      "events": [
        {
          "type": "damage",
          "src": "ai-289784",
          "tgt": "ai-289784",
          "dmg": 8,
          "skill": "wither",
          "crit": false
        },
        {
          "type": "heal",
          "src": "ai-1b84e7",
          "tgt": "ai-1b84e7",
          "amt": 8,
          "skill": "prayer"
        },
        {
          "type": "heal",
          "src": "ai-ef2b85",
          "tgt": "ai-2e99d1",
          "amt": 8,
          "skill": "healing_totem"
        },
        {
          "type": "heal",
          "src": "ai-ef2b85",
          "tgt": "ai-289784",
          "amt": 8,
          "skill": "healing_totem"
        },
        {
          "type": "damage",
          "src": "ai-ef2b85",
          "tgt": "ai-1b84e7",
          "dmg": 1,
          "skill": "searing_totem",
          "crit": false
        },
        {
          "type": "damage",
          "src": "ai-ef2b85",
          "tgt": "ai-7a35f7",
          "dmg": 1,
          "skill": "searing_totem",
          "crit": false
        },
        {
          "type": "damage",
          "src": "ai-ef2b85",
          "tgt": "ai-9e6803",
          "dmg": 1,
          "skill": "searing_totem",
          "crit": false
        },
        {
          "type": "buff",
          "src": "ai-2e99d1",
          "tgt": "ai-2e99d1",
          "buff": "taunt"
        },
        {
          "type": "buff",
          "src": "ai-53fbfb",
          "tgt": "ai-7fe566",
          "buff": "seal_of_judgment"
        },
        {
          "type": "damage",
          "src": "ai-e82373",
          "tgt": "ai-1b84e7",
          "dmg": 29,
          "skill": "power_shot",
          "crit": false
        },
        {
          "type": "damage",
          "src": "ai-7fe566",
          "tgt": "ai-2e99d1",
          "dmg": 8,
          "skill": "double_strike",
          "crit": false
        },
        {
          "type": "buff",
          "src": "ai-9e6803",
          "tgt": "ai-9e6803",
          "buff": "grave_thorns"
        },
        {
          "type": "damage",
          "src": "ai-289784",
          "tgt": "ai-7a35f7",
          "dmg": 9,
          "skill": "attack",
          "crit": false
        },
        {
          "type": "damage",
          "src": "ai-7a35f7",
          "tgt": "ai-289784",
          "dmg": 13,
          "skill": "attack",
          "crit": true
        },
        {
          "type": "damage",
          "src": "ai-289784",
          "tgt": "ai-7a35f7",
          "dmg": 8,
          "skill": "ward",
          "crit": false
        },
        {
          "type": "death",
          "unit": "ai-1b84e7",
          "killer": "ai-e82373"
        }
      ]
    },
    {
      "turn": 18,
      "events": [
        {
          "type": "damage",
          "src": "ai-289784",
          "tgt": "ai-289784",
          "dmg": 8,
          "skill": "wither",
          "crit": false
        },
        {
          "type": "damage",
          "src": "ai-ef2b85",
          "tgt": "ai-7a35f7",
          "dmg": 1,
          "skill": "searing_totem",
          "crit": false
        },
        {
          "type": "damage",
          "src": "ai-ef2b85",
          "tgt": "ai-9e6803",
          "dmg": 1,
          "skill": "searing_totem",
          "crit": false
        },
        {
          "type": "move",
          "unit": "ai-e82373",
          "to": [
            5,
            6
          ]
        },
        {
          "type": "damage",
          "src": "ai-2e99d1",
          "tgt": "ai-9e6803",
          "dmg": 3,
          "skill": "shield_bash",
          "crit": false
        },
        {
          "type": "buff",
          "src": "ai-2e99d1",
          "tgt": "ai-9e6803",
          "buff": "shield_bash"
        },
        {
          "type": "damage",
          "src": "ai-53fbfb",
          "tgt": "ai-7fe566",
          "dmg": 20,
          "skill": "power_shot",
          "crit": false
        },
        {
          "type": "buff",
          "src": "ai-ef2b85",
          "tgt": "ai-ef2b85",
          "buff": "earthgrasp"
        },
        {
          "type": "damage",
          "src": "ai-7a35f7",
          "tgt": "ai-289784",
          "dmg": 4,
          "skill": "shield_bash",
          "crit": false
        },
        {
          "type": "buff",
          "src": "ai-7a35f7",
          "tgt": "ai-289784",
          "buff": "shield_bash"
        },
        {
          "type": "damage",
          "src": "ai-7fe566",
          "tgt": "ai-2e99d1",
          "dmg": 9,
          "skill": "attack",
          "crit": false
        }
      ]
    },
    {
      "turn": 19,
      "events": [
        {
          "type": "damage",
          "src": "ai-289784",
          "tgt": "ai-289784",
          "dmg": 8,
          "skill": "wither",
          "crit": false
        },
        {
          "type": "damage",
          "src": "ai-ef2b85",
          "tgt": "ai-7a35f7",
          "dmg": 1,
          "skill": "searing_totem",
          "crit": false
        },
        {
          "type": "damage",
          "src": "ai-ef2b85",
          "tgt": "ai-9e6803",
          "dmg": 1,
          "skill": "searing_totem",
          "crit": false
        },
        {
          "type": "move",
          "unit": "ai-53fbfb",
          "to": [
            7,
            6
          ]
        },
        {
          "type": "move",
          "unit": "ai-e82373",
          "to": [
            6,
            7
          ]
        },
        {
          "type": "move",
          "unit": "ai-ef2b85",
          "to": [
            9,
            6
          ]
        },
        {
          "type": "heal",
          "src": "ai-2e99d1",
          "tgt": "ai-2e99d1",
          "amt": 30,
          "skill": "holy_ground"
        },
        {
          "type": "buff",
          "src": "ai-2e99d1",
          "tgt": "ai-2e99d1",
          "buff": "holy_ground"
        },
        {
          "type": "heal",
          "src": "ai-7a35f7",
          "tgt": "ai-7a35f7",
          "amt": 15,
          "skill": "holy_ground"
        },
        {
          "type": "buff",
          "src": "ai-7a35f7",
          "tgt": "ai-7a35f7",
          "buff": "holy_ground"
        },
        {
          "type": "damage",
          "src": "ai-7fe566",
          "tgt": "ai-2e99d1",
          "dmg": 9,
          "skill": "attack",
          "crit": false
        }
      ]
    },
    {
      "turn": 20,
      "events": [
        {
          "type": "buff",
          "src": "ai-2e99d1",
          "tgt": "ai-2e99d1",
          "buff": "bulwark"
        },
        {
          "type": "buff",
          "src": "ai-289784",
          "tgt": "ai-9e6803",
          "buff": "wither"
        },
        {
          "type": "damage",
          "src": "ai-53fbfb",
          "tgt": "ai-7fe566",
          "dmg": 23,
          "skill": "rebuke",
          "crit": false
        },
        {
          "type": "damage",
          "src": "ai-e82373",
          "tgt": "ai-7fe566",
          "dmg": 9,
          "skill": "crippling_shot",
          "crit": false
        },
        {
          "type": "buff",
          "src": "ai-e82373",
          "tgt": "ai-7fe566",
          "buff": "crippling_shot"
        },
        {
          "type": "buff",
          "src": "ai-ef2b85",
          "tgt": "ai-ef2b85",
          "buff": "healing_totem"
        },
        {
          "type": "buff",
          "src": "ai-7a35f7",
          "tgt": "ai-7a35f7",
          "buff": "bulwark"
        },
        {
          "type": "buff",
          "src": "ai-7fe566",
          "tgt": "ai-7fe566",
          "buff": "ward"
        },
        {
          "type": "damage",
          "src": "ai-9e6803",
          "tgt": "ai-2e99d1",
          "dmg": 2,
          "skill": "attack",
          "crit": false
        }
      ]
    },
    {
      "turn": 21,
      "events": [
        {
          "type": "damage",
          "src": "ai-9e6803",
          "tgt": "ai-9e6803",
          "dmg": 8,
          "skill": "wither",
          "crit": false
        },
        {
          "type": "heal",
          "src": "ai-ef2b85",
          "tgt": "ai-2e99d1",
          "amt": 8,
          "skill": "healing_totem"
        },
        {
          "type": "heal",
          "src": "ai-ef2b85",
          "tgt": "ai-289784",
          "amt": 8,
          "skill": "healing_totem"
        },
        {
          "type": "move",
          "unit": "ai-53fbfb",
          "to": [
            6,
            5
          ]
        },
        {
          "type": "move",
          "unit": "ai-e82373",
          "to": [
            5,
            6
          ]
        },
        {
          "type": "damage",
          "src": "ai-289784",
          "tgt": "ai-9e6803",
          "dmg": 8,
          "skill": "double_strike",
          "crit": false
        },
        {
          "type": "damage",
          "src": "ai-7fe566",
          "tgt": "ai-2e99d1",
          "dmg": 8,
          "skill": "double_strike",
          "crit": false
        },
        {
          "type": "damage",
          "src": "ai-9e6803",
          "tgt": "ai-289784",
          "dmg": 19,
          "skill": "soul_rend",
          "crit": false
        },
        {
          "type": "buff",
          "src": "ai-9e6803",
          "tgt": "ai-289784",
          "buff": "soul_rend"
        },
        {
          "type": "damage",
          "src": "ai-ef2b85",
          "tgt": "ai-7a35f7",
          "dmg": 1,
          "skill": "ranged_attack",
          "crit": false
        },
        {
          "type": "damage",
          "src": "ai-2e99d1",
          "tgt": "ai-9e6803",
          "dmg": 8,
          "skill": "attack",
          "crit": false
        },
        {
          "type": "damage",
          "src": "ai-7a35f7",
          "tgt": "ai-289784",
          "dmg": 9,
          "skill": "attack",
          "crit": false
        }
      ]
    },
    {
      "turn": 22,
      "events": [
        {
          "type": "damage",
          "src": "ai-9e6803",
          "tgt": "ai-9e6803",
          "dmg": 8,
          "skill": "wither",
          "crit": false
        },
        {
          "type": "heal",
          "src": "ai-ef2b85",
          "tgt": "ai-2e99d1",
          "amt": 8,
          "skill": "healing_totem"
        },
        {
          "type": "heal",
          "src": "ai-ef2b85",
          "tgt": "ai-289784",
          "amt": 8,
          "skill": "healing_totem"
        },
        {
          "type": "move",
          "unit": "ai-e82373",
          "to": [
            6,
            7
          ]
        },
        {
          "type": "buff",
          "src": "ai-289784",
          "tgt": "ai-289784",
          "buff": "ward"
        },
        {
          "type": "buff",
          "src": "ai-53fbfb",
          "tgt": "ai-9e6803",
          "buff": "seal_of_judgment"
        },
        {
          "type": "buff",
          "src": "ai-7a35f7",
          "tgt": "ai-7a35f7",
          "buff": "taunt"
        },
        {
          "type": "buff",
          "src": "ai-7fe566",
          "tgt": "ai-ef2b85",
          "buff": "wither"
        },
        {
          "type": "buff",
          "src": "ai-9e6803",
          "tgt": "ai-e82373",
          "buff": "grave_chains"
        },
        {
          "type": "damage",
          "src": "ai-2e99d1",
          "tgt": "ai-9e6803",
          "dmg": 10,
          "skill": "attack",
          "crit": false
        }
      ]
    },
    {
      "turn": 23,
      "events": [
        {
          "type": "damage",
          "src": "ai-ef2b85",
          "tgt": "ai-ef2b85",
          "dmg": 8,
          "skill": "wither",
          "crit": false
        },
        {
          "type": "damage",
          "src": "ai-9e6803",
          "tgt": "ai-9e6803",
          "dmg": 8,
          "skill": "wither",
          "crit": false
        },
        {
          "type": "heal",
          "src": "ai-ef2b85",
          "tgt": "ai-2e99d1",
          "amt": 8,
          "skill": "healing_totem"
        },
        {
          "type": "heal",
          "src": "ai-ef2b85",
          "tgt": "ai-289784",
          "amt": 8,
          "skill": "healing_totem"
        },
        {
          "type": "heal",
          "src": "ai-ef2b85",
          "tgt": "ai-ef2b85",
          "amt": 8,
          "skill": "healing_totem"
        },
        {
          "type": "move",
          "unit": "ai-53fbfb",
          "to": [
            7,
            6
          ]
        },
        {
          "type": "buff",
          "src": "ai-2e99d1",
          "tgt": "ai-2e99d1",
          "buff": "taunt"
        },
        {
          "type": "damage",
          "src": "ai-e82373",
          "tgt": null,
          "dmg": 8,
          "skill": "volley",
          "crit": false
        },
        {
          "type": "buff",
          "src": "ai-e82373",
          "tgt": "ai-e82373",
          "buff": "volley"
        },
        {
          "type": "damage",
          "src": "ai-7a35f7",
          "tgt": "ai-289784",
          "dmg": 4,
          "skill": "shield_bash",
          "crit": false
        },
        {
          "type": "buff",
          "src": "ai-7a35f7",
          "tgt": "ai-289784",
          "buff": "shield_bash"
        },
        {
          "type": "buff",
          "src": "ai-9e6803",
          "tgt": "ai-9e6803",
          "buff": "undying_will"
        },
        {
          "type": "damage",
          "src": "ai-7fe566",
          "tgt": "ai-2e99d1",
          "dmg": 1,
          "skill": "attack",
          "crit": false
        }
      ]
    },
    {
      "turn": 24,
      "events": [
        {
          "type": "damage",
          "src": "ai-ef2b85",
          "tgt": "ai-ef2b85",
          "dmg": 8,
          "skill": "wither",
          "crit": false
        },
        {
          "type": "heal",
          "src": "ai-ef2b85",
          "tgt": "ai-2e99d1",
          "amt": 8,
          "skill": "healing_totem"
        },
        {
          "type": "heal",
          "src": "ai-ef2b85",
          "tgt": "ai-289784",
          "amt": 8,
          "skill": "healing_totem"
        },
        {
          "type": "heal",
          "src": "ai-ef2b85",
          "tgt": "ai-ef2b85",
          "amt": 8,
          "skill": "healing_totem"
        },
        {
          "type": "move",
          "unit": "ai-7a35f7",
          "to": [
            7,
            8
          ]
        },
        {
          "type": "damage",
          "src": "ai-2e99d1",
          "tgt": "ai-9e6803",
          "dmg": 3,
          "skill": "shield_bash",
          "crit": false
        },
        {
          "type": "buff",
          "src": "ai-2e99d1",
          "tgt": "ai-9e6803",
          "buff": "shield_bash"
        },
        {
          "type": "damage",
          "src": "ai-53fbfb",
          "tgt": "ai-7fe566",
          "dmg": 7,
          "skill": "ranged_attack",
          "crit": false
        },
        {
          "type": "damage",
          "src": "ai-7fe566",
          "tgt": "ai-53fbfb",
          "dmg": 8,
          "skill": "ward",
          "crit": false
        },
        {
          "type": "damage",
          "src": "ai-e82373",
          "tgt": "ai-9e6803",
          "dmg": 22,
          "skill": "ranged_attack",
          "crit": true
        },
        {
          "type": "damage",
          "src": "ai-7fe566",
          "tgt": "ai-2e99d1",
          "dmg": 9,
          "skill": "attack",
          "crit": false
        },
        {
          "type": "heal",
          "src": "ai-9e6803",
          "tgt": "ai-9e6803",
          "amt": 39,
          "skill": "undying_will"
        }
      ]
    },
    {
      "turn": 25,
      "events": [
        {
          "type": "damage",
          "src": "ai-ef2b85",
          "tgt": "ai-ef2b85",
          "dmg": 8,
          "skill": "wither",
          "crit": false
        },
        {
          "type": "move",
          "unit": "ai-53fbfb",
          "to": [
            6,
            6
          ]
        },
        {
          "type": "damage",
          "src": "ai-289784",
          "tgt": "ai-7a35f7",
          "dmg": 8,
          "skill": "double_strike",
          "crit": false
        },
        {
          "type": "damage",
          "src": "ai-e82373",
          "tgt": "ai-9e6803",
          "dmg": 26,
          "skill": "power_shot",
          "crit": false
        },
        {
          "type": "heal",
          "src": "ai-7a35f7",
          "tgt": "ai-7a35f7",
          "amt": 15,
          "skill": "holy_ground"
        },
        {
          "type": "buff",
          "src": "ai-7a35f7",
          "tgt": "ai-7a35f7",
          "buff": "holy_ground"
        },
        {
          "type": "damage",
          "src": "ai-7fe566",
          "tgt": "ai-2e99d1",
          "dmg": 8,
          "skill": "double_strike",
          "crit": false
        },
        {
          "type": "damage",
          "src": "ai-2e99d1",
          "tgt": "ai-7fe566",
          "dmg": 9,
          "skill": "attack",
          "crit": false
        },
        {
          "type": "damage",
          "src": "ai-7fe566",
          "tgt": "ai-2e99d1",
          "dmg": 8,
          "skill": "ward",
          "crit": false
        }
      ]
    },
    {
      "turn": 26,
      "events": [
        {
          "type": "buff",
          "src": "ai-2e99d1",
          "tgt": "ai-2e99d1",
          "buff": "bulwark"
        },
        {
          "type": "buff",
          "src": "ai-289784",
          "tgt": "ai-7a35f7",
          "buff": "wither"
        },
        {
          "type": "damage",
          "src": "ai-53fbfb",
          "tgt": "ai-7a35f7",
          "dmg": 22,
          "skill": "rebuke",
          "crit": false
        },
        {
          "type": "damage",
          "src": "ai-e82373",
          "tgt": "ai-7a35f7",
          "dmg": 8,
          "skill": "crippling_shot",
          "crit": false
        },
        {
          "type": "buff",
          "src": "ai-e82373",
          "tgt": "ai-7a35f7",
          "buff": "crippling_shot"
        },
        {
          "type": "buff",
          "src": "ai-7a35f7",
          "tgt": "ai-7a35f7",
          "buff": "bulwark"
        },
        {
          "type": "damage",
          "src": "ai-9e6803",
          "tgt": "ai-289784",
          "dmg": 19,
          "skill": "soul_rend",
          "crit": false
        },
        {
          "type": "buff",
          "src": "ai-9e6803",
          "tgt": "ai-289784",
          "buff": "soul_rend"
        },
        {
          "type": "damage",
          "src": "ai-7fe566",
          "tgt": "ai-2e99d1",
          "dmg": 1,
          "skill": "attack",
          "crit": false
        }
      ]
    },
    {
      "turn": 27,
      "events": [
        {
          "type": "damage",
          "src": "ai-7a35f7",
          "tgt": "ai-7a35f7",
          "dmg": 8,
          "skill": "wither",
          "crit": false
        },
        {
          "type": "move",
          "unit": "ai-e82373",
          "to": [
            5,
            6
          ]
        },
        {
          "type": "heal",
          "src": "ai-2e99d1",
          "tgt": "ai-2e99d1",
          "amt": 30,
          "skill": "holy_ground"
        },
        {
          "type": "buff",
          "src": "ai-2e99d1",
          "tgt": "ai-2e99d1",
          "buff": "holy_ground"
        },
        {
          "type": "buff",
          "src": "ai-53fbfb",
          "tgt": "ai-7a35f7",
          "buff": "seal_of_judgment"
        },
        {
          "type": "buff",
          "src": "ai-ef2b85",
          "tgt": "ai-ef2b85",
          "buff": "healing_totem"
        },
        {
          "type": "buff",
          "src": "ai-7fe566",
          "tgt": "ai-7fe566",
          "buff": "ward"
        },
        {
          "type": "buff",
          "src": "ai-9e6803",
          "tgt": "ai-9e6803",
          "buff": "grave_thorns"
        },
        {
          "type": "damage",
          "src": "ai-289784",
          "tgt": "ai-9e6803",
          "dmg": 9,
          "skill": "attack",
          "crit": false
        },
        {
          "type": "damage",
          "src": "ai-9e6803",
          "tgt": "ai-289784",
          "dmg": 12,
          "skill": "attack",
          "crit": false
        },
        {
          "type": "damage",
          "src": "ai-7a35f7",
          "tgt": "ai-2e99d1",
          "dmg": 1,
          "skill": "attack",
          "crit": false
        }
      ]
    },
    {
      "turn": 28,
      "events": [
        {
          "type": "damage",
          "src": "ai-7a35f7",
          "tgt": "ai-7a35f7",
          "dmg": 8,
          "skill": "wither",
          "crit": false
        },
        {
          "type": "heal",
          "src": "ai-ef2b85",
          "tgt": "ai-2e99d1",
          "amt": 8,
          "skill": "healing_totem"
        },
        {
          "type": "heal",
          "src": "ai-ef2b85",
          "tgt": "ai-289784",
          "amt": 8,
          "skill": "healing_totem"
        },
        {
          "type": "heal",
          "src": "ai-ef2b85",
          "tgt": "ai-53fbfb",
          "amt": 8,
          "skill": "healing_totem"
        },
        {
          "type": "heal",
          "src": "ai-ef2b85",
          "tgt": "ai-ef2b85",
          "amt": 8,
          "skill": "healing_totem"
        },
        {
          "type": "move",
          "unit": "ai-e82373",
          "to": [
            4,
            5
          ]
        },
        {
          "type": "damage",
          "src": "ai-53fbfb",
          "tgt": "ai-7a35f7",
          "dmg": 18,
          "skill": "power_shot",
          "crit": false
        },
        {
          "type": "buff",
          "src": "ai-7a35f7",
          "tgt": "ai-7a35f7",
          "buff": "taunt"
        },
        {
          "type": "buff",
          "src": "ai-7fe566",
          "tgt": "ai-2e99d1",
          "buff": "wither"
        },
        {
          "type": "damage",
          "src": "ai-2e99d1",
          "tgt": "ai-7a35f7",
          "dmg": 1,
          "skill": "attack",
          "crit": false
        },
        {
          "type": "damage",
          "src": "ai-289784",
          "tgt": "ai-7a35f7",
          "dmg": 1,
          "skill": "attack",
          "crit": false
        }
      ]
    },
    {
      "turn": 29,
      "events": [
        {
          "type": "damage",
          "src": "ai-2e99d1",
          "tgt": "ai-2e99d1",
          "dmg": 8,
          "skill": "wither",
          "crit": false
        },
        {
          "type": "damage",
          "src": "ai-7a35f7",
          "tgt": "ai-7a35f7",
          "dmg": 8,
          "skill": "wither",
          "crit": false
        },
        {
          "type": "heal",
          "src": "ai-ef2b85",
          "tgt": "ai-2e99d1",
          "amt": 8,
          "skill": "healing_totem"
        },
        {
          "type": "heal",
          "src": "ai-ef2b85",
          "tgt": "ai-289784",
          "amt": 8,
          "skill": "healing_totem"
        },
        {
          "type": "heal",
          "src": "ai-ef2b85",
          "tgt": "ai-ef2b85",
          "amt": 8,
          "skill": "healing_totem"
        },
        {
          "type": "move",
          "unit": "ai-53fbfb",
          "to": [
            5,
            5
          ]
        },
        {
          "type": "buff",
          "src": "ai-2e99d1",
          "tgt": "ai-2e99d1",
          "buff": "taunt"
        },
        {
          "type": "buff",
          "src": "ai-289784",
          "tgt": "ai-289784",
          "buff": "ward"
        },
        {
          "type": "damage",
          "src": "ai-7fe566",
          "tgt": "ai-2e99d1",
          "dmg": 8,
          "skill": "double_strike",
          "crit": false
        },
        {
          "type": "death",
          "unit": "ai-7a35f7",
          "killer": "ai-7a35f7"
        }
      ]
    },
    {
      "turn": 30,
      "events": [
        {
          "type": "damage",
          "src": "ai-2e99d1",
          "tgt": "ai-2e99d1",
          "dmg": 8,
          "skill": "wither",
          "crit": false
        },
        {
          "type": "heal",
          "src": "ai-ef2b85",
          "tgt": "ai-2e99d1",
          "amt": 8,
          "skill": "healing_totem"
        },
        {
          "type": "heal",
          "src": "ai-ef2b85",
          "tgt": "ai-289784",
          "amt": 8,
          "skill": "healing_totem"
        },
        {
          "type": "move",
          "unit": "ai-e82373",
          "to": [
            3,
            6
          ]
        },
        {
          "type": "damage",
          "src": "ai-2e99d1",
          "tgt": "ai-9e6803",
          "dmg": 3,
          "skill": "shield_bash",
          "crit": false
        },
        {
          "type": "buff",
          "src": "ai-2e99d1",
          "tgt": "ai-9e6803",
          "buff": "shield_bash"
        },
        {
          "type": "damage",
          "src": "ai-289784",
          "tgt": "ai-9e6803",
          "dmg": 4,
          "skill": "double_strike",
          "crit": false
        },
        {
          "type": "damage",
          "src": "ai-53fbfb",
          "tgt": "ai-7fe566",
          "dmg": 7,
          "skill": "ranged_attack",
          "crit": false
        },
        {
          "type": "damage",
          "src": "ai-7fe566",
          "tgt": "ai-53fbfb",
          "dmg": 8,
          "skill": "ward",
          "crit": false
        },
        {
          "type": "damage",
          "src": "ai-7fe566",
          "tgt": "ai-2e99d1",
          "dmg": 13,
          "skill": "attack",
          "crit": true
        },
        {
          "type": "death",
          "unit": "ai-9e6803",
          "killer": "ai-289784"
        }
      ]
    },
    {
      "turn": 31,
      "events": [
        {
          "type": "damage",
          "src": "ai-2e99d1",
          "tgt": "ai-2e99d1",
          "dmg": 8,
          "skill": "wither",
          "crit": false
        },
        {
          "type": "heal",
          "src": "ai-ef2b85",
          "tgt": "ai-2e99d1",
          "amt": 8,
          "skill": "healing_totem"
        },
        {
          "type": "heal",
          "src": "ai-ef2b85",
          "tgt": "ai-289784",
          "amt": 8,
          "skill": "healing_totem"
        },
        {
          "type": "move",
          "unit": "ai-289784",
          "to": [
            6,
            8
          ]
        },
        {
          "type": "move",
          "unit": "ai-53fbfb",
          "to": [
            4,
            6
          ]
        },
        {
          "type": "move",
          "unit": "ai-e82373",
          "to": [
            3,
            7
          ]
        },
        {
          "type": "damage",
          "src": "ai-2e99d1",
          "tgt": "ai-7fe566",
          "dmg": 9,
          "skill": "attack",
          "crit": false
        },
        {
          "type": "death",
          "unit": "ai-7fe566",
          "killer": "ai-2e99d1"
        }
      ]
    }
  ],
  "summary": {
    "team_a_total_damage": 632,
    "team_a_total_healing": 298,
    "team_a_kills": 5,
    "team_a_deaths": 0,
    "team_b_total_damage": 347,
    "team_b_total_healing": 107,
    "team_b_kills": 1,
    "team_b_deaths": 5,
    "first_blood_turn": 9,
    "first_blood_killer": "ai-e82373",
    "first_blood_victim": "ai-cb0908",
    "mvp": "ai-e82373",
    "mvp_damage": 188,
    "mvp_kills": 3
  }
}